{
  "로욜라국제대학 교육과정": {
    "글로벌경제전공": {
      "교육목표": "글로벌경제전공은 글로벌 시대의 경제 환경에 대한 엄밀한 분석력과 국제적 경쟁력을 갖춘 합리적이고 창의적인 경제 전문인재를 양성하는 것을 목표로 하고 있습니다. 국제경제의 다양한 현상에 대해 이해하고 해석하는 능력 양성을 위한 기본적인 소양을 배양하고 현실 경제에 응용이 가능한 실용적인 학문적 역량을 키우기 위해 경제학, 국제경제학, 경영학과의 융합교육을 실시합니다.",
      "전공 이수요건": {
        "학점 이수요건": {
          "전인교육과정": {
            "공통필수": 16,
            "공통선택": 6,
            "소계": 22
          },
          "전공입문":16,
          "전공": {
            "전공필수": 6,
            "전공선택": 36,
            "전공소계": 42
          },
          "총이수학점": 126
        },
        "교과목 이수요건": {
          "전공 입문": {
            "Pre-Major Courses": [
              {
                "Course Code": "GIS1001",
                "Title": "글로벌융합학부입문"
              },
              {
                "Course Code": "GIS2001",
                "Title": "미시경제원론"
              },
              {
                "Course Code": "GIS2002",
                "Title": "회계학"
              },
              {
                "Course Code": "GIS2003",
                "Title": "The Art of Storytelling"
              },
              {
                "Course Code": "GIS2004",
                "Title": "인공지능프로그래밍"
              },
              {
                "Course Code": "GIS2005",
                "Title": "거시경제원론"
              }
            ],
            "Credits": 16
          },
          "전공 필수": {
            "Required Courses": [
              {
                "Course Code": "GEC3001",
                "Title": "미시경제학"
              },
              {
                "Course Code": "GEC3002",
                "Title": "거시경제학"
              }
            ],
            "Credits": 6
          },
          "전공 선택": {
            "Electives": [
              {
                "Course Code": "GEC4001",
                "Title": "화폐와금융"
              },
              {
                "Course Code": "GEC4002",
                "Title": "국제무역이론"
              },
              {
                "Course Code": "GEC4003",
                "Title": "국제금융이론"
              },
              {
                "Course Code": "GEC4004",
                "Title": "산업조직론"
              },
              {
                "Course Code": "GEC4005",
                "Title": "계량경제학"
              },
              {
                "Course Code": "GEC4006",
                "Title": "한국경제의발전"
              },
              {
                "Course Code": "GEC4007",
                "Title": "경제개발이론"
              },
              {
                "Course Code": "GEC4008",
                "Title": "경제수학"
              }
            ],
            "Credits": 36
          }
        }
      },
      "과목정보":{
        "전공입문": [
      {
        "과목코드": "GIS1001",
        "교과목명": "글로벌융학학부입문",
        "강의시간": "1시간",
        "학점": "1학점",
        "내용": "신입생이 입학한 첫 학기에 개설되며 학과장 주관으로 글로벌융합학부의 세부 전공에 대해 소개하는 시간을 갖는다. 전공 주임 교수가 세부 전공에 대한 소개를 담당하고, 각 전공과 관련된 내부 교수와 외부 인사들의 특강으로 세부 전공에 대한 이해를 돕는다."
      },
      {
        "과목코드": "GIS2001",
        "교과목명": "미시경제원론",
        "강의시간": "3시간",
        "학점": "3학점",
        "내용": "경제생활의 기본적 현상과 개별 경제 주체인 가계, 기업의 경제활동의 동기 및 행동을 이해하고 이를 기초로 시장경제에서의 가격 결정과 자원 배분이 어떻게 이루어지는가를 학습한다. 또한 개별 시장의 특성 및 어떤 조건하에서 자원 배분의 효율성이 달성될 수 있는가에 대해서 다룬다."
      },
      {
        "과목코드": "GIS2002",
        "교과목명": "회계학",
        "강의시간": "3시간",
        "학점": "3학점",
        "내용": "기업경영의 언어라고 할 수 있는 회계정보를 작성하는 데에 사용되는 회계개념, 회계원칙을 회계정보 처리 과정의 최종 산물인 재무제표를 작성하기 위하여 사용되는 회계기법의 기본원리와 회계장부의 구조를 공부한다."
      },
      {
        "과목코드": "GIS2003",
        "교과목명": "The Art of Storytelling",
        "강의시간": "3시간",
        "학점": "3학점",
        "내용": "본 과목은 콘텐츠 창작의 기본이 되는 스토리 아트와 스토리텔링 크래프트를 집중적으로 다룬다. 스토리 개발, 다양한 목적 및 매체에 따른 스토리텔링 전략과 방법 탐색, 창의적인 적용과 응용의 과정을 실습한다."
      },
      {
        "과목코드": "GIS2004",
        "교과목명": "인공지능프로그래밍",
        "강의시간": "3시간",
        "학점": "3학점",
        "내용": "인공지능 관련 전문성을 높이고 인재양성을 위해 전 신입생 대상으로 제공되는 과목으로, 인공지능 프로그래밍의 기초를 학습한다."
      },
      {
        "과목코드": "GIS2005",
        "교과목명": "거시경제원론",
        "강의시간": "3시간",
        "학점": "3학점",
        "내용": "각 경제단위(가계, 기업, 정부, 해외부문)들의 행동과 그 상호관계를 통해 국민경제전체를 살펴본다. 국민소득, 소비, 저축, 투자, 고용, 물가, 통화, 임금, 이자 등의 거시경제변수의 결정과정과 변동을 분석한다. 성장과 경기변동, 경제문제 해결을 위한 정부의 역할 등을 다룬다."
      }
    ],
    "전공필수": [
      {
        "과목코드": "GEC3001",
        "교과목명": "미시경제학",
        "강의시간": "3시간",
        "학점": "3학점",
        "내용": "시장경제 하에서 자원배분, 소득분배가 결정되는 원리를 배운다. 수요와 공급의 개념, 소비자균형과 시장수요, 생산과 생산비의 이론, 생산물시장과 생산요소시장의 균형, 그리고 일반균형·후생경제학의 기초이론을 다룬다."
      },
      {
        "과목코드": "GKE3002",
        "교과목명": "거시경제학",
        "강의시간": "3시간",
        "학점": "3학점",
        "내용": "국가 경제의 여러 현상, 특히 국민소득의 변동, 경제성장, 인플레이션, 실업률 등을 이해하기 위해 집계변수들의 동향을 파악하고 이에 대한 분석의 틀을 제공하는 한편, 경기변동을 완화하고 지속적인 경제성장을 달성하기 위한 정부의 정책 수단과 방법, 효과, 한계 등을 논의한다."
      }
    ],
    "전공선택": [
      {
        "과목코드": "GKE4001",
        "교과목명": "화폐와금융",
        "강의시간": "3시간",
        "학점": "3학점",
        "내용": "채권, 주식, 대출시장의 미시적 기초와 이론적 기반을 소개하고, 금융기관의 경영관리와 위험관리에 관한 기초이론을 공부한다. 또한 중앙은행의 기능과 화폐수요와 공급, 금융정책이론과 전달경로 등 금융정책의 기본적인 내용들을 다룬다."
      },
      {
        "과목코드": "GKE4002",
        "교과목명": "국제무역이론",
        "강의시간": "3시간",
        "학점": "3학점",
        "내용": "국제무역의 순수이론과 무역정책을 공부한다. 비교생산비설과 요소 부존론에 의한 무역이론과 그 실증적 검정, 국제무역과 경제성장의 관계를 다룬다. 또한 독점적 경쟁시장에서의 무역의 이득에 대해서도 학습한다. 무역정책은, 관세 및 비관세 장벽의 경제적 효과, 수출보조금의 경제적 효과, 경제통합이론 등을 다룬다."
      },
      {
        "과목코드": "GKE4003",
        "교과목명": "국제금융이론",
        "강의시간": "3시간",
        "학점": "3학점",
        "내용": "국제수지의 이론과 정책 및 국제통화제도와 관련된 제 문제를 공부한다. 외환시장과 환율의 결정이론, 상이한 환율제도 하에서의 국제수지의 조정이론과 조정정책, 그리고 국제통화 제도와 국제금융시장의 기능과 전개과정을 다룬다."
      },
      {
        "과목코드": "GKE4004",
        "교과목명": "산업조직론",
        "강의시간": "3시간",
        "학점": "3학점",
        "내용": "산업의 구조적 특성에 따라 기업들의 전략적 선택과 시장에서의 경쟁 성과가 어떻게 달라지는지를 연구한다. 즉 완전 경쟁, 독점, 과점 산업에서 기업들이 선택하는 가격, 산출량, 투자, 광고, R&D 등 다양한 전략들을 다루고, 이들이 산업의 경제적 성과에 미치는 영향을 이론 및 실증적으로 분석한다. 그리고 산업성과를 개선하는 다양한 정책의 방안을 모색한다."
      },
      {
        "과목코드": "GKE4005",
        "교과목명": "계량경제학",
        "강의시간": "3시간",
        "학점": "3학점",
        "내용": "통계적 추정 및 가설검정 방법을 기초로 선형 회귀분석 및 그 응용에 관한 이론을 공부한다. 모형의 선정, 다중공선성, 이분산, 자기상관 등 실제 경제자료를 다룰 때 발생할 수 있는 문제점을 파악하고 이러한 문제를 해결할 수 있는 능력을 배양한다."
      },
      {
        "과목코드": "GKE4006",
        "교과목명": "한국경제의발전",
        "강의시간": "3시간",
        "학점": "3학점",
        "내용": "한국경제의 구조적 변천과 성장요인을 산업구조, 소비, 투자, 금융, 재정 그리고 무역과 국제수지 등의 각 분야별로 연구한다."
      },
      {
        "과목코드": "GKE4007",
        "교과목명": "경제개발이론",
        "강의시간": "3시간",
        "학점": "3학점",
        "내용": "본 강좌는 어떠한 요소가 한 국가를 발전하게 만드는지, 또한 어떠한 이유로 한 국가의 발전이 저해되는지를 경제학 이론과 실증경제 분석을 통하여 검토한다. 향후 세계은행 등 국제개발기구, 국내 개발원조센터, 및 대학원 진학을 목표로 하는 학생들을 염두해두고 디자인되어 집중적인 토론 수업으로 진행된다."
      },
      {
        "과목코드": "GKE4008",
        "교과목명": "경제수학",
        "강의시간": "3시간",
        "학점": "3학점",
        "내용": "경제이론과 통계학을 이해하기 위해 필요한 행렬과 벡터, 미분과 적분의 개념을 소개한다. 또한 경제 모형의 분석에 필요한 편미분과 최적화 문제의 해법을 다룬다. 엄격한 증명보다는 경제학 문제들을 통하여 수학의 실제적인 적용 방법을 학습하는 것을 목적으로 한다."
      }
    ]
      }
    }
  }
}